python_fsm_handler/StateHandler.py
python_fsm_handler/__init__.py
python_fsm_handler-0.0.3.dist-info/METADATA
python_fsm_handler-0.0.3.dist-info/WHEEL
python_fsm_handler-0.0.3.dist-info/licenses/LICENSE
python_fsm_handler-0.0.3.dist-info/RECORD
