Metadata-Version: 2.3
Name: python_fsm_handler
Version: 0.0.3
Summary: Class to handle Finite State Machines
Project-URL: Homepage, https://github.com/creminem94/python_fsm
Project-URL: Issues, https://github.com/creminem94/python_fsm/issues
Author-email: Simone Cremasco <simonecremasco94@gmail.com>
License-File: LICENSE
Classifier: License :: OSI Approved :: MIT License
Classifier: Operating System :: OS Independent
Classifier: Programming Language :: Python :: 3
Requires-Python: >=3.8
